main.py
mseep_daraja-0.1.3.dist-info/METADATA
mseep_daraja-0.1.3.dist-info/WHEEL
mseep_daraja-0.1.3.dist-info/entry_points.txt
mseep_daraja-0.1.3.dist-info/top_level.txt
mseep_daraja-0.1.3.dist-info/RECORD
