Metadata-Version: 2.4
Name: mseep-daraja
Version: 0.1.3
Summary: Add your description here
Author-email: mseep <support@skydeck.ai>
Requires-Python: >=3.13
Requires-Dist: boto3>=1.37.22
Requires-Dist: httpx>=0.28.1
Requires-Dist: ipykernel>=6.29.5
Requires-Dist: langchain-mongodb>=0.6.0
Requires-Dist: langchain-openai>=0.3.11
Requires-Dist: mcp[cli]>=1.5.0
Requires-Dist: pymongo>=4.11.3
Requires-Dist: python-dotenv>=1.1.0
Requires-Dist: unstructured-client>=0.30.6
